sprites/__init__.py
sprites/checkpoint.py
sprites/client.py
sprites/exceptions.py
sprites/exec.py
sprites/filesystem.py
sprites/policy.py
sprites/py.typed
sprites/services.py
sprites/session.py
sprites/sprite.py
sprites/types.py
sprites/websocket.py
sprites_py-0.0.1a1.dist-info/METADATA
sprites_py-0.0.1a1.dist-info/WHEEL
sprites_py-0.0.1a1.dist-info/entry_points.txt
sprites_py-0.0.1a1.dist-info/top_level.txt
sprites_py-0.0.1a1.dist-info/RECORD
